avocentpdulib/__init__.py
avocentpdulib/avocent_pdu.py
avocentpdulib/errors.py
avocentpdulib-0.0.1.dist-info/METADATA
avocentpdulib-0.0.1.dist-info/WHEEL
avocentpdulib-0.0.1.dist-info/top_level.txt
avocentpdulib-0.0.1.dist-info/RECORD
