Metadata-Version: 2.1
Name: avocentpdulib
Version: 0.0.1
Summary: Feature-rich methods to control avocent pdu's in python
Home-page: https://github.com/Howaner/avocentpdulib
Author: Howaner
Author-email: me@reiterfranz.de
License: UNKNOWN
Platform: UNKNOWN
Classifier: Programming Language :: Python :: 3
Classifier: License :: OSI Approved :: MIT License
Classifier: Operating System :: OS Independent
Requires-Python: >3.5.2
